setup.py
rvim/__init__.py
rvim/cli.py
rvim/client.py
rvim/server.py
rvim/vimplugin.py
rvim.egg-info/PKG-INFO
rvim.egg-info/SOURCES.txt
rvim.egg-info/dependency_links.txt
rvim.egg-info/entry_points.txt
rvim.egg-info/top_level.txt