Metadata-Version: 1.1
Name: rvim
Version: 0.0.2
Summary: Remote VIM-integrated fileserver and client
Home-page: https://github.com/mfichman/rvim
Author: Matt Fichman
Author-email: matt.fichman@gmail.com
License: MIT
Keywords: vim,remote
Platform: UNKNOWN
Requires: bottle
Requires: gevent
